{
  "type": "FeatureCollection",
  "features": [
    {
      "type": "Feature",
      "geometry": {
        "type": "Point",
        "coordinates": [
          16.3691, 48.203
        ]
      },
      "properties": {
        "name": "06. Mai 1877"
      }
    }
  ]
}