{
  "type": "FeatureCollection",
  "features": [
    {
      "type": "Feature",
      "geometry": {
        "type": "Point",
        "coordinates": [
          16.36645, 48.20778
        ]
      },
      "properties": {
        "name": "02. November 1877"
      }
    }
  ]
}