{
  "type": "FeatureCollection",
  "features": [
    {
      "type": "Feature",
      "geometry": {
        "type": "Point",
        "coordinates": [
          8.68417, 50.11552
        ]
      },
      "properties": {
        "name": "31. August 1879"
      }
    }
  ]
}