{
  "type": "FeatureCollection",
  "features": [
    {
      "type": "Feature",
      "geometry": {
        "type": "Point",
        "coordinates": [
          17.10674, 48.14816
        ]
      },
      "properties": {
        "name": "11. September 1882"
      }
    }
  ]
}