{
  "type": "FeatureCollection",
  "features": [
    {
      "type": "Feature",
      "geometry": {
        "type": "Point",
        "coordinates": [
          2.92711, 51.2119
        ]
      },
      "properties": {
        "name": "12. August 1888"
      }
    }
  ]
}