{
  "type": "FeatureCollection",
  "features": [
    {
      "type": "Feature",
      "geometry": {
        "type": "Point",
        "coordinates": [
          11.97947, 51.48158
        ]
      },
      "properties": {
        "name": "20. September 1891"
      }
    }
  ]
}