{
  "type": "FeatureCollection",
  "features": [
    {
      "type": "Feature",
      "geometry": {
        "type": "Point",
        "coordinates": [
          15.91352, 47.78709
        ]
      },
      "properties": {
        "name": "25. Mai 1900"
      }
    }
  ]
}