{
  "type": "FeatureCollection",
  "features": [
    {
      "type": "Feature",
      "geometry": {
        "type": "Point",
        "coordinates": [
          11.24626, 43.77925
        ]
      },
      "properties": {
        "name": "16. April 1901"
      }
    }
  ]
}