{
  "type": "FeatureCollection",
  "features": [
    {
      "type": "Feature",
      "geometry": {
        "type": "Point",
        "coordinates": [
          11.63749, 46.73901
        ]
      },
      "properties": {
        "name": "21. Juli 1901"
      }
    }
  ]
}