{
  "type": "FeatureCollection",
  "features": [
    {
      "type": "Feature",
      "geometry": {
        "type": "Point",
        "coordinates": [
          14.47783, 47.02251
        ]
      },
      "properties": {
        "name": "29. August 1901"
      }
    }
  ]
}