{
  "type": "FeatureCollection",
  "features": [
    {
      "type": "Feature",
      "geometry": {
        "type": "Point",
        "coordinates": [
          8.96004, 46.01008
        ]
      },
      "properties": {
        "name": "07. Juni 1903"
      }
    }
  ]
}