{
  "type": "FeatureCollection",
  "features": [
    {
      "type": "Feature",
      "geometry": {
        "type": "Point",
        "coordinates": [
          7.50435, 43.77649
        ]
      },
      "properties": {
        "name": "24. April 1911"
      }
    }
  ]
}