{
  "type": "FeatureCollection",
  "features": [
    {
      "type": "Feature",
      "geometry": {
        "type": "Point",
        "coordinates": [
          15.8075, 47.775833
        ]
      },
      "properties": {
        "name": "09. Juli 1912"
      }
    }
  ]
}