{
  "type": "FeatureCollection",
  "features": [
    {
      "type": "Feature",
      "geometry": {
        "type": "Point",
        "coordinates": [
          9.84327, 46.49937
        ]
      },
      "properties": {
        "name": "28. August 1913"
      }
    }
  ]
}