{
  "type": "FeatureCollection",
  "features": [
    {
      "type": "Feature",
      "geometry": {
        "type": "Point",
        "coordinates": [
          4.88969, 52.37403
        ]
      },
      "properties": {
        "name": "23. Mai 1914"
      }
    }
  ]
}