{
  "type": "FeatureCollection",
  "features": [
    {
      "type": "Feature",
      "geometry": {
        "type": "Point",
        "coordinates": [
          15.8241, 47.64224
        ]
      },
      "properties": {
        "name": "02. September 1915"
      }
    }
  ]
}