{
  "type": "FeatureCollection",
  "features": [
    {
      "type": "Feature",
      "geometry": {
        "type": "Point",
        "coordinates": [
          13.78243, 47.60998
        ]
      },
      "properties": {
        "name": "18. Juni 1921"
      }
    }
  ]
}