{
  "type": "FeatureCollection",
  "features": [
    {
      "type": "Feature",
      "geometry": {
        "type": "Point",
        "coordinates": [
          11.29326, 47.94602
        ]
      },
      "properties": {
        "name": "30. Juli 1922"
      }
    }
  ]
}