{
  "type": "FeatureCollection",
  "features": [
    {
      "type": "Feature",
      "geometry": {
        "type": "Point",
        "coordinates": [
          10.25848, 46.77696
        ]
      },
      "properties": {
        "name": "04. September 1923"
      }
    }
  ]
}