{
  "type": "FeatureCollection",
  "features": [
    {
      "type": "Feature",
      "geometry": {
        "type": "Point",
        "coordinates": [
          8.23975, 48.7606
        ]
      },
      "properties": {
        "name": "01. Juli 1923"
      }
    }
  ]
}