{
  "type": "FeatureCollection",
  "features": [
    {
      "type": "Feature",
      "geometry": {
        "type": "Point",
        "coordinates": [
          11.58817, 46.41147
        ]
      },
      "properties": {
        "name": "11. August 1925"
      }
    }
  ]
}