{
  "type": "FeatureCollection",
  "features": [
    {
      "type": "Feature",
      "geometry": {
        "type": "Point",
        "coordinates": [
          16.338015, 48.234046
        ]
      },
      "properties": {
        "name": "12. April 1927"
      }
    }
  ]
}