{
  "type": "FeatureCollection",
  "features": [
    {
      "type": "Feature",
      "geometry": {
        "type": "Point",
        "coordinates": [
          16.361139, 48.210333
        ]
      },
      "properties": {
        "name": "15. April 1927"
      }
    }
  ]
}