{
  "type": "FeatureCollection",
  "features": [
    {
      "type": "Feature",
      "geometry": {
        "type": "Point",
        "coordinates": [
          13.76667, 45.66667
        ]
      },
      "properties": {
        "name": "13. April 1928"
      }
    }
  ]
}