{
  "type": "FeatureCollection",
  "features": [
    {
      "type": "Feature",
      "geometry": {
        "type": "Point",
        "coordinates": [
          10.74085, 47.55631
        ]
      },
      "properties": {
        "name": "28. August 1928"
      }
    }
  ]
}