{
  "type": "FeatureCollection",
  "features": [
    {
      "type": "Feature",
      "geometry": {
        "type": "Point",
        "coordinates": [16.38222, 48.21336]
      },
      "properties": {
         "id": "pmb168783",
         "title": "Praterstraße 16",
         "lat": "48.21336",
         "lon": "16.38222",
         "timestamp": ["1862-05-15"],
         "importance": 1, 
        "abbr": "Wohngebäude (K.WHS)", 
        "type": "Wohngebäude", 
        "wohnort": [
         {

         "p_name": "Louise Schnitzler",

         "p_id": "#12701"
         }, 
         {

         "p_name": "Johann Schnitzler",

         "p_id": "#12695"
         }, 
         {

         "p_name": "Arthur Schnitzler",

         "p_id": ""
         }]
      }
      }, 
    {
      "type": "Feature",
      "geometry": {
        "type": "Point",
        "coordinates": [16.373056, 48.208333]
      },
      "properties": {
         "id": "pmb50",
         "title": "Wien",
         "lat": "48.208333",
         "lon": "16.373056",
         "timestamp": ["1862-05-15"],
         "importance": 1, 
        "wikipedia": "https://de.wikipedia.org/wiki/Wien", 
        "wikidata": "http://www.wikidata.org/entity/Q1741", 
        "geonames": "https://sws.geonames.org/2761369/ https://sws.geonames.org/2761333/", 
        "abbr": "A.ADM2", 
        "type": "Verwaltungsgebiet"
      }
      }, 
    {
      "type": "Feature",
      "geometry": {
        "type": "Point",
        "coordinates": [15.84704, 47.70466]
      },
      "properties": {
         "id": "pmb796",
         "title": "Thalhof",
         "lat": "47.70466",
         "lon": "15.84704",
         "timestamp": ["1869-01-01", "1869-01-02"],
         "importance": 2, 
        "geonames": "https://sws.geonames.org/2763740/", 
        "abbr": "S.HTL", 
        "type": "Hotel"
      }
      }, 
    {
      "type": "Feature",
      "geometry": {
        "type": "Point",
        "coordinates": [15.83333, 47.7]
      },
      "properties": {
         "id": "pmb483",
         "title": "Reichenau an der Rax",
         "lat": "47.7",
         "lon": "15.83333",
         "timestamp": ["1869-01-01", "1869-01-02"],
         "importance": 2, 
        "wikipedia": "https://de.wikipedia.org/wiki/Reichenau_an_der_Rax", 
        "wikidata": "http://www.wikidata.org/entity/Q665243", 
        "geonames": "https://sws.geonames.org/2767775/", 
        "abbr": "A.ADM3", 
        "type": "Verwaltungsgebiet"
      }
      }
  ]
}