{
  "type": "FeatureCollection",
  "features": [
    {
      "type": "Feature",
      "geometry": {
        "type": "Point",
        "coordinates": [15.84704, 47.70466]
      },
      "properties": {
         "id": "pmb796",
         "title": "Thalhof",
         "lat": "47.70466",
         "lon": "15.84704",
         "timestamp": ["1869-01-01", "1869-01-02"],
         "importance": "2"
      }
      }, 
    {
      "type": "Feature",
      "geometry": {
        "type": "Point",
        "coordinates": [15.83333, 47.7]
      },
      "properties": {
         "id": "pmb483",
         "title": "Reichenau an der Rax",
         "lat": "47.7",
         "lon": "15.83333",
         "timestamp": ["1869-01-01", "1869-01-02"],
         "importance": "2"
      }
      }
  ]
}