{
  "type": "FeatureCollection",
  "features": [
    {
      "geometry": {
        "type": "Point",
        "coordinates": [ 16.38222, 48.21336 ]
      },
      "properties": {
        "abbr": "Wohngebäude (K.WHS)",
        "wohnort": [
          { "p_id":"#12701", "p_name":"Louise Schnitzler" },
          { "p_id":"#12695", "p_name":"Johann Schnitzler" },
          { "p_id":"#338728", "p_name":"Caroline Schwarz" },
          { "p_id":"#104502", "p_name":"Paul Schwarz" },
          { "p_id":"", "p_name":"Arthur Schnitzler" }
        ],
        "importance": 1,
        "timestamp": [ "1862-05-15" ],
        "title": "Praterstraße 16",
        "type": "Wohngebäude Residential building",
        "id": "pmb168783"
      },
      "type": "Feature"
    },
    {
      "geometry": {
        "type": "Point",
        "coordinates": [ 16.373056, 48.208333 ]
      },
      "properties": {
        "abbr": "A.ADM2",
        "importance": 1,
        "timestamp": [ "1862-05-15" ],
        "wikipedia": "https:\/\/de.wikipedia.org\/wiki\/Wien",
        "geonames": "https:\/\/sws.geonames.org\/2761369\/",
        "title": "Wien",
        "type": "Verwaltungsgebiet Administrative district",
        "wikidata": "http:\/\/www.wikidata.org\/entity\/Q1741",
        "id": "pmb50"
      },
      "type": "Feature"
    },
    {
      "geometry": {
        "type": "Point",
        "coordinates": [ 15.84704, 47.70466 ]
      },
      "properties": {
        "abbr": "S.HTL",
        "importance": 2,
        "timestamp": [ "1869-01-01", "1869-01-02" ],
        "geonames": "https:\/\/sws.geonames.org\/2763740\/",
        "title": "Thalhof",
        "type": "Hotel Hotel",
        "id": "pmb796"
      },
      "type": "Feature"
    },
    {
      "geometry": {
        "type": "Point",
        "coordinates": [ 15.83333, 47.7 ]
      },
      "properties": {
        "abbr": "A.ADM3",
        "importance": 2,
        "timestamp": [ "1869-01-01", "1869-01-02" ],
        "wikipedia": "https:\/\/de.wikipedia.org\/wiki\/Reichenau_an_der_Rax",
        "geonames": "https:\/\/sws.geonames.org\/2767775\/",
        "title": "Reichenau an der Rax",
        "type": "Verwaltungsgebiet Administrative district",
        "wikidata": "http:\/\/www.wikidata.org\/entity\/Q665243",
        "id": "pmb483"
      },
      "type": "Feature"
    }
  ]
}