{
  "type": "FeatureCollection",
  "features": [
    {
      "type": "Feature",
      "geometry": {
        "type": "Point",
        "coordinates": [8.48447, 47.0555]
      },
      "properties": {
         "id": "pmb91598",
         "title": "Rigi Kulm",
         "lat": "47.0555",
         "lon": "8.48447",
         "timestamp": ["1871-07-01", "1871-07-02", "1871-07-03", "1871-07-04", "1871-07-05", "1871-07-06", "1871-07-07", "1871-07-08", "1871-07-09", "1871-07-10", "1871-07-11", "1871-07-12", "1871-07-13", "1871-07-14", "1871-07-15", "1871-07-16", "1871-07-17", "1871-07-18", "1871-07-19", "1871-07-20", "1871-07-21", "1871-07-22", "1871-07-23", "1871-07-24", "1871-07-25", "1871-07-26", "1871-07-27", "1871-07-28", "1871-07-29", "1871-07-30", "1871-07-31"],
         "importance": "31", 
        "geonames": "https://sws.geonames.org/2660093/", 
        "abbr": "P.PPL", 
        "type": "Besiedelter Ort"
      }
      }
  ]
}