{
  "type": "FeatureCollection",
  "features": [
    {
      "type": "Feature",
      "geometry": {
        "type": "Point",
        "coordinates": [13.043176, 47.81233]
      },
      "properties": {
         "id": "pmb152",
         "title": "Grand Hotel de L’Europe, G. Jung",
         "lat": "47.81233",
         "lon": "13.043176",
         "timestamp": ["1871-01-01"],
         "importance": 1, 
        "wikipedia": "https://de.wikipedia.org/wiki/Hotel_de_l%E2%80%99Europe_(Salzburg)", 
        "wikidata": "http://www.wikidata.org/entity/Q16831871", 
        "abbr": "Hotel (K.HTL)", 
        "type": "Hotel"
      }
      }, 
    {
      "type": "Feature",
      "geometry": {
        "type": "Point",
        "coordinates": [13.04532, 47.80067]
      },
      "properties": {
         "id": "pmb30",
         "title": "Salzburg",
         "lat": "47.80067",
         "lon": "13.04532",
         "timestamp": ["1871-01-01"],
         "importance": 1, 
        "wikipedia": "https://de.wikipedia.org/wiki/Salzburg", 
        "wikidata": "http://www.wikidata.org/entity/Q34713", 
        "geonames": "https://sws.geonames.org/2766818/", 
        "abbr": "A.ADM2", 
        "type": "Verwaltungsgebiet"
      }
      }, 
    {
      "type": "Feature",
      "geometry": {
        "type": "Point",
        "coordinates": [8.48447, 47.0555]
      },
      "properties": {
         "id": "pmb91598",
         "title": "Rigi Kulm",
         "lat": "47.0555",
         "lon": "8.48447",
         "timestamp": ["1871-07-01", "1871-07-02", "1871-07-03", "1871-07-04", "1871-07-05", "1871-07-06", "1871-07-07", "1871-07-08", "1871-07-09", "1871-07-10", "1871-07-11", "1871-07-12", "1871-07-13", "1871-07-14", "1871-07-15", "1871-07-16", "1871-07-17", "1871-07-18", "1871-07-19", "1871-07-20", "1871-07-21", "1871-07-22", "1871-07-23", "1871-07-24", "1871-07-25", "1871-07-26", "1871-07-27", "1871-07-28", "1871-07-29", "1871-07-30", "1871-07-31", "1871-08-01", "1871-08-02", "1871-08-03", "1871-08-04", "1871-08-05", "1871-08-06", "1871-08-07", "1871-08-08", "1871-08-09", "1871-08-10", "1871-08-11", "1871-08-12", "1871-08-13", "1871-08-14", "1871-08-15", "1871-08-16", "1871-08-17", "1871-08-18", "1871-08-19", "1871-08-20", "1871-08-21", "1871-08-22", "1871-08-23", "1871-08-24", "1871-08-25", "1871-08-26", "1871-08-27", "1871-08-28", "1871-08-29", "1871-08-30", "1871-08-31"],
         "importance": 62, 
        "geonames": "https://sws.geonames.org/2660093/", 
        "abbr": "P.PPL", 
        "type": "Besiedelter Ort"
      }
      }
  ]
}