{
  "type": "FeatureCollection",
  "features": [
    {
      "type": "Feature",
      "geometry": {
        "type": "Point",
        "coordinates": [16.207378, 47.96739]
      },
      "properties": {
         "id": "pmb246533",
         "title": "Villa Mandl",
         "lat": "47.96739",
         "lon": "16.207378",
         "timestamp": ["1873-07-01", "1873-07-02", "1873-07-03", "1873-07-04", "1873-07-05", "1873-07-06", "1873-07-07", "1873-07-08", "1873-07-09", "1873-07-10", "1873-07-11", "1873-07-12", "1873-07-13", "1873-07-14", "1873-07-15", "1873-07-16", "1873-07-17", "1873-07-18", "1873-07-19", "1873-07-20", "1873-07-21", "1873-07-22", "1873-07-23", "1873-07-24", "1873-07-25", "1873-07-26", "1873-07-27", "1873-07-28", "1873-07-29", "1873-07-30", "1873-07-31", "1873-08-01", "1873-08-02", "1873-08-03", "1873-08-04", "1873-08-05", "1873-08-06", "1873-08-07", "1873-08-08", "1873-08-09", "1873-08-10", "1873-08-11", "1873-08-12", "1873-08-13", "1873-08-14", "1873-08-15", "1873-08-16", "1873-08-17", "1873-08-18", "1873-08-19", "1873-08-20", "1873-08-21", "1873-08-22", "1873-08-23", "1873-08-24", "1873-08-25", "1873-08-26", "1873-08-27", "1873-08-28", "1873-08-29", "1873-08-30", "1873-08-31"],
         "importance": 62, 
        "abbr": "Wohngebäude (K.WHS)", 
        "type": "Wohngebäude Residential building"
      }
      }, 
    {
      "type": "Feature",
      "geometry": {
        "type": "Point",
        "coordinates": [16.206282759, 47.967944698]
      },
      "properties": {
         "id": "pmb246538",
         "title": "Vöslauer Sommerarena",
         "lat": "47.967944698",
         "lon": "16.206282759",
         "timestamp": ["1873-07-01", "1873-07-02", "1873-07-03", "1873-07-04", "1873-07-05", "1873-07-06", "1873-07-07", "1873-07-08", "1873-07-09", "1873-07-10", "1873-07-11", "1873-07-12", "1873-07-13", "1873-07-14", "1873-07-15", "1873-07-16", "1873-07-17", "1873-07-18", "1873-07-19", "1873-07-20", "1873-07-21", "1873-07-22", "1873-07-23", "1873-07-24", "1873-07-25", "1873-07-26", "1873-07-27", "1873-07-28", "1873-07-29", "1873-07-30", "1873-07-31", "1873-08-01", "1873-08-02", "1873-08-03", "1873-08-04", "1873-08-05", "1873-08-06", "1873-08-07", "1873-08-08", "1873-08-09", "1873-08-10", "1873-08-11", "1873-08-12", "1873-08-13", "1873-08-14", "1873-08-15", "1873-08-16", "1873-08-17", "1873-08-18", "1873-08-19", "1873-08-20", "1873-08-21", "1873-08-22", "1873-08-23", "1873-08-24", "1873-08-25", "1873-08-26", "1873-08-27", "1873-08-28", "1873-08-29", "1873-08-30", "1873-08-31"],
         "importance": 62, 
        "abbr": "Theater (K.THE)", 
        "type": "Theater Theatre", 
        "arbeitsort": [
         {

         "p_name": "Josef Sprinz",

         "p_id": "#25279"
         }]
      }
      }, 
    {
      "type": "Feature",
      "geometry": {
        "type": "Point",
        "coordinates": [16.21359, 47.96533]
      },
      "properties": {
         "id": "pmb992",
         "title": "Bad Vöslau",
         "lat": "47.96533",
         "lon": "16.21359",
         "timestamp": ["1873-07-01", "1873-07-02", "1873-07-03", "1873-07-04", "1873-07-05", "1873-07-06", "1873-07-07", "1873-07-08", "1873-07-09", "1873-07-10", "1873-07-11", "1873-07-12", "1873-07-13", "1873-07-14", "1873-07-15", "1873-07-16", "1873-07-17", "1873-07-18", "1873-07-19", "1873-07-20", "1873-07-21", "1873-07-22", "1873-07-23", "1873-07-24", "1873-07-25", "1873-07-26", "1873-07-27", "1873-07-28", "1873-07-29", "1873-07-30", "1873-07-31", "1873-08-01", "1873-08-02", "1873-08-03", "1873-08-04", "1873-08-05", "1873-08-06", "1873-08-07", "1873-08-08", "1873-08-09", "1873-08-10", "1873-08-11", "1873-08-12", "1873-08-13", "1873-08-14", "1873-08-15", "1873-08-16", "1873-08-17", "1873-08-18", "1873-08-19", "1873-08-20", "1873-08-21", "1873-08-22", "1873-08-23", "1873-08-24", "1873-08-25", "1873-08-26", "1873-08-27", "1873-08-28", "1873-08-29", "1873-08-30", "1873-08-31"],
         "importance": 62, 
        "wikipedia": "https://de.wikipedia.org/wiki/Bad_V%C3%B6slau", 
        "wikidata": "http://www.wikidata.org/entity/Q798800", 
        "geonames": "https://sws.geonames.org/2782043/", 
        "abbr": "P.PPLA3", 
        "type": "Hauptstadt Capital"
      }
      }
  ]
}