{
  "type": "FeatureCollection",
  "features": [
    {
      "type": "Feature",
      "geometry": {
        "type": "Point",
        "coordinates": [16.21359, 47.96533]
      },
      "properties": {
         "id": "pmb992",
         "title": "Bad Vöslau",
         "lat": "47.96533",
         "lon": "16.21359",
         "timestamp": ["1875-07-16", "1875-07-17"],
         "importance": 2, 
        "wikipedia": "https://de.wikipedia.org/wiki/Bad_V%C3%B6slau", 
        "wikidata": "http://www.wikidata.org/entity/Q798800", 
        "geonames": "https://sws.geonames.org/2782043/", 
        "abbr": "P.PPLA3", 
        "type": "Hauptstadt"
      }
      }, 
    {
      "type": "Feature",
      "geometry": {
        "type": "Point",
        "coordinates": [16.21168888888889, 47.96718055555556]
      },
      "properties": {
         "id": "pmb253426",
         "title": "Bad [Bad Vöslau]",
         "lat": "47.96718055555556",
         "lon": "16.21168888888889",
         "timestamp": ["1875-07-17"],
         "importance": 1, 
        "wikipedia": "https://de.wikipedia.org/wiki/Thermalbad_Bad_V%C3%B6slau", 
        "wikidata": "http://www.wikidata.org/entity/Q97285560", 
        "abbr": "Schwimmbad (K.BAD)", 
        "type": "Schwimmbad"
      }
      }
  ]
}