{
  "type": "FeatureCollection",
  "features": [
    {
      "geometry": {
        "type": "Point",
        "coordinates": [ 16.21359, 47.96533 ]
      },
      "properties": {
        "abbr": "P.PPLA3",
        "importance": 2,
        "timestamp": [ "1875-07-16", "1875-07-17" ],
        "wikipedia": "https:\/\/de.wikipedia.org\/wiki\/Bad_V%C3%B6slau",
        "geonames": "https:\/\/sws.geonames.org\/2782043\/",
        "title": "Bad Vöslau",
        "type": "Hauptstadt Capital",
        "wikidata": "http:\/\/www.wikidata.org\/entity\/Q798800",
        "id": "pmb992"
      },
      "type": "Feature"
    },
    {
      "geometry": {
        "type": "Point",
        "coordinates": [ 16.21168888888889, 47.96718055555556 ]
      },
      "properties": {
        "abbr": "Schwimmbad (K.BAD)",
        "importance": 1,
        "timestamp": [ "1875-07-17" ],
        "wikipedia": "https:\/\/de.wikipedia.org\/wiki\/Thermalbad_Bad_V%C3%B6slau",
        "title": "Bad [Bad Vöslau]",
        "type": "Schwimmbad Swimming pool",
        "wikidata": "http:\/\/www.wikidata.org\/entity\/Q97285560",
        "id": "pmb253426"
      },
      "type": "Feature"
    }
  ]
}