{
  "type": "FeatureCollection",
  "features": [
    {
      "geometry": {
        "type": "Point",
        "coordinates": [ 16.373056, 48.208333 ]
      },
      "properties": {
        "abbr": "A.ADM2",
        "importance": 2,
        "timestamp": [ "1876-03-15", "1876-03-29" ],
        "wikipedia": "https:\/\/de.wikipedia.org\/wiki\/Wien",
        "geonames": "https:\/\/sws.geonames.org\/2761369\/",
        "title": "Wien",
        "type": "Verwaltungsgebiet Administrative district",
        "wikidata": "http:\/\/www.wikidata.org\/entity\/Q1741",
        "id": "pmb50"
      },
      "type": "Feature"
    },
    {
      "geometry": {
        "type": "Point",
        "coordinates": [ 16.363819, 48.20334 ]
      },
      "properties": {
        "abbr": "Ordination",
        "importance": 2,
        "timestamp": [ "1876-03-15", "1876-03-29" ],
        "title": "Wohnung und Ordination Johann Schnitzler Burgring 1",
        "type": "Ordination Medical practice",
        "id": "pmb168765"
      },
      "type": "Feature"
    },
    {
      "geometry": {
        "type": "Point",
        "coordinates": [ 16.375, 48.205139 ]
      },
      "properties": {
        "abbr": "Theater (K.THE)",
        "importance": 1,
        "timestamp": [ "1876-03-15" ],
        "wikipedia": "https:\/\/de.wikipedia.org\/wiki\/Ronacher",
        "title": "Ronacher",
        "type": "Theater Theatre",
        "wikidata": "http:\/\/www.wikidata.org\/entity\/Q1244587",
        "id": "pmb19",
        "arbeitsort": [
          { "p_id":"#18926", "p_name":"Anna Judic" },
          { "p_id":"#2702", "p_name":"Heinrich Laube" }
        ]
      },
      "type": "Feature"
    },
    {
      "geometry": {
        "type": "Point",
        "coordinates": [ 16.371296264238, 48.202432234197 ]
      },
      "properties": {
        "wiengeschichtewiki": "https:\/\/www.geschichtewiki.wien.gv.at\/Special:URIResolver\/?curid=26893",
        "abbr": "R.ST",
        "importance": 1,
        "timestamp": [ "1876-03-29" ],
        "wikipedia": "https:\/\/de.wikipedia.org\/wiki\/Wiener_Ringstra%C3%9Fe",
        "geonames": "https:\/\/sws.geonames.org\/8181703\/",
        "title": "Ringstraße",
        "type": "Straße Street",
        "wikidata": "http:\/\/www.wikidata.org\/entity\/Q46232",
        "id": "pmb112"
      },
      "type": "Feature"
    }
  ]
}