{
  "type": "FeatureCollection",
  "features": [
    {
      "geometry": {
        "type": "Point",
        "coordinates": [ 16.373056, 48.208333 ]
      },
      "properties": {
        "abbr": "A.ADM2",
        "importance": 2,
        "timestamp": [ "1877-06-16", "1877-06-30" ],
        "wikipedia": "https:\/\/de.wikipedia.org\/wiki\/Wien",
        "geonames": "https:\/\/sws.geonames.org\/2761369\/",
        "title": "Wien",
        "type": "Verwaltungsgebiet Administrative district",
        "wikidata": "http:\/\/www.wikidata.org\/entity\/Q1741",
        "id": "pmb50"
      },
      "type": "Feature"
    },
    {
      "geometry": {
        "type": "Point",
        "coordinates": [ 16.363819, 48.20334 ]
      },
      "properties": {
        "abbr": "Ordination",
        "importance": 2,
        "timestamp": [ "1877-06-16", "1877-06-30" ],
        "title": "Wohnung und Ordination Johann Schnitzler Burgring 1",
        "type": "Ordination Medical practice",
        "id": "pmb168765"
      },
      "type": "Feature"
    },
    {
      "geometry": {
        "type": "Point",
        "coordinates": [ 16.3691, 48.203 ]
      },
      "properties": {
        "abbr": "Oper (K.OPR)",
        "importance": 2,
        "timestamp": [ "1877-06-16", "1877-06-30" ],
        "wikipedia": "https:\/\/de.wikipedia.org\/wiki\/Wiener_Staatsoper",
        "title": "Oper",
        "type": "Oper Opera house",
        "wikidata": "http:\/\/www.wikidata.org\/entity\/Q209937",
        "id": "pmb15",
        "arbeitsort": [ { "p_id":"#2762", "p_name":"Hans Gregor" } ]
      },
      "type": "Feature"
    }
  ]
}