{
  "type": "FeatureCollection",
  "features": [
    {
      "geometry": {
        "type": "Point",
        "coordinates": [ 16.373056, 48.208333 ]
      },
      "properties": {
        "abbr": "A.ADM2",
        "importance": 30,
        "timestamp": [
          "1882-07-01",
          "1882-07-02",
          "1882-07-03",
          "1882-07-04",
          "1882-07-05",
          "1882-07-06",
          "1882-07-07",
          "1882-07-08",
          "1882-07-09",
          "1882-07-10",
          "1882-07-11",
          "1882-07-12",
          "1882-07-13",
          "1882-07-14",
          "1882-07-15",
          "1882-07-16",
          "1882-07-17",
          "1882-07-18",
          "1882-07-19",
          "1882-07-20",
          "1882-07-21",
          "1882-07-22",
          "1882-07-23",
          "1882-07-24",
          "1882-07-25",
          "1882-07-26",
          "1882-07-27",
          "1882-07-28",
          "1882-07-29",
          "1882-07-30"
        ],
        "wikipedia": "https:\/\/de.wikipedia.org\/wiki\/Wien",
        "geonames": "https:\/\/sws.geonames.org\/2761369\/",
        "title": "Wien",
        "type": "Verwaltungsgebiet Administrative district",
        "wikidata": "http:\/\/www.wikidata.org\/entity\/Q1741",
        "id": "pmb50"
      },
      "type": "Feature"
    },
    {
      "geometry": {
        "type": "Point",
        "coordinates": [ 16.363819, 48.20334 ]
      },
      "properties": {
        "abbr": "Ordination",
        "importance": 30,
        "timestamp": [
          "1882-07-01",
          "1882-07-02",
          "1882-07-03",
          "1882-07-04",
          "1882-07-05",
          "1882-07-06",
          "1882-07-07",
          "1882-07-08",
          "1882-07-09",
          "1882-07-10",
          "1882-07-11",
          "1882-07-12",
          "1882-07-13",
          "1882-07-14",
          "1882-07-15",
          "1882-07-16",
          "1882-07-17",
          "1882-07-18",
          "1882-07-19",
          "1882-07-20",
          "1882-07-21",
          "1882-07-22",
          "1882-07-23",
          "1882-07-24",
          "1882-07-25",
          "1882-07-26",
          "1882-07-27",
          "1882-07-28",
          "1882-07-29",
          "1882-07-30"
        ],
        "title": "Wohnung und Ordination Johann Schnitzler Burgring 1",
        "type": "Ordination Medical practice",
        "id": "pmb168765"
      },
      "type": "Feature"
    },
    {
      "geometry": {
        "type": "Point",
        "coordinates": [ 16.372564182283, 48.201265597319 ]
      },
      "properties": {
        "abbr": "Konzertsaal (K.KNZ)",
        "importance": 1,
        "timestamp": [ "1882-07-15" ],
        "title": "Musikverein",
        "type": "Konzertsaal Concert hall",
        "id": "pmb516"
      },
      "type": "Feature"
    },
    {
      "geometry": {
        "type": "Point",
        "coordinates": [ 9.50266, 47.00601 ]
      },
      "properties": {
        "abbr": "P.PPL",
        "importance": 1,
        "timestamp": [ "1882-07-31" ],
        "geonames": "https:\/\/sws.geonames.org\/2661644\/",
        "title": "Bad Ragaz",
        "type": "Besiedelter Ort Populated place",
        "id": "pmb49990"
      },
      "type": "Feature"
    }
  ]
}