{
  "type": "FeatureCollection",
  "features": [
    {
      "geometry": {
        "type": "Point",
        "coordinates": [ 16.373056, 48.208333 ]
      },
      "properties": {
        "abbr": "A.ADM2",
        "importance": 29,
        "timestamp": [
          "1884-09-02",
          "1884-09-03",
          "1884-09-04",
          "1884-09-05",
          "1884-09-06",
          "1884-09-07",
          "1884-09-08",
          "1884-09-09",
          "1884-09-10",
          "1884-09-11",
          "1884-09-12",
          "1884-09-13",
          "1884-09-14",
          "1884-09-15",
          "1884-09-16",
          "1884-09-17",
          "1884-09-18",
          "1884-09-19",
          "1884-09-20",
          "1884-09-21",
          "1884-09-22",
          "1884-09-23",
          "1884-09-24",
          "1884-09-25",
          "1884-09-26",
          "1884-09-27",
          "1884-09-28",
          "1884-09-29",
          "1884-09-30"
        ],
        "wikipedia": "https:\/\/de.wikipedia.org\/wiki\/Wien",
        "geonames": "https:\/\/sws.geonames.org\/2761369\/",
        "title": "Wien",
        "type": "Verwaltungsgebiet Administrative district",
        "wikidata": "http:\/\/www.wikidata.org\/entity\/Q1741",
        "id": "pmb50"
      },
      "type": "Feature"
    },
    {
      "geometry": {
        "type": "Point",
        "coordinates": [ 16.363819, 48.20334 ]
      },
      "properties": {
        "abbr": "Ordination",
        "importance": 29,
        "timestamp": [
          "1884-09-02",
          "1884-09-03",
          "1884-09-04",
          "1884-09-05",
          "1884-09-06",
          "1884-09-07",
          "1884-09-08",
          "1884-09-09",
          "1884-09-10",
          "1884-09-11",
          "1884-09-12",
          "1884-09-13",
          "1884-09-14",
          "1884-09-15",
          "1884-09-16",
          "1884-09-17",
          "1884-09-18",
          "1884-09-19",
          "1884-09-20",
          "1884-09-21",
          "1884-09-22",
          "1884-09-23",
          "1884-09-24",
          "1884-09-25",
          "1884-09-26",
          "1884-09-27",
          "1884-09-28",
          "1884-09-29",
          "1884-09-30"
        ],
        "title": "Wohnung und Ordination Johann Schnitzler Burgring 1",
        "type": "Ordination Medical practice",
        "id": "pmb168765"
      },
      "type": "Feature"
    },
    {
      "geometry": {
        "type": "Point",
        "coordinates": [ 16.36645, 48.20778 ]
      },
      "properties": {
        "abbr": "Theater (K.THE)",
        "importance": 2,
        "timestamp": [ "1884-09-04", "1884-09-08" ],
        "title": "Burgtheater [Altes Burgtheater]",
        "type": "Theater Theatre",
        "wikidata": "http:\/\/www.wikidata.org\/entity\/Q45350189",
        "id": "pmb185621"
      },
      "type": "Feature"
    },
    {
      "geometry": {
        "type": "Point",
        "coordinates": [ 13.61893, 47.71109 ]
      },
      "properties": {
        "abbr": "P.PPL",
        "importance": 1,
        "timestamp": [ "1884-09-01" ],
        "wikipedia": "https:\/\/de.wikipedia.org\/wiki\/Bad_Ischl",
        "geonames": "https:\/\/sws.geonames.org\/2782052\/",
        "title": "Bad Ischl",
        "type": "Besiedelter Ort Populated place",
        "wikidata": "http:\/\/www.wikidata.org\/entity\/Q250984",
        "id": "pmb213"
      },
      "type": "Feature"
    }
  ]
}