{
  "type": "FeatureCollection",
  "features": [
    {
      "geometry": {
        "type": "Point",
        "coordinates": [ 16.373056, 48.208333 ]
      },
      "properties": {
        "abbr": "A.ADM2",
        "importance": 30,
        "timestamp": [
          "1887-06-01",
          "1887-06-02",
          "1887-06-03",
          "1887-06-04",
          "1887-06-05",
          "1887-06-06",
          "1887-06-07",
          "1887-06-08",
          "1887-06-09",
          "1887-06-10",
          "1887-06-11",
          "1887-06-12",
          "1887-06-13",
          "1887-06-14",
          "1887-06-15",
          "1887-06-16",
          "1887-06-17",
          "1887-06-18",
          "1887-06-19",
          "1887-06-20",
          "1887-06-21",
          "1887-06-22",
          "1887-06-23",
          "1887-06-24",
          "1887-06-25",
          "1887-06-26",
          "1887-06-27",
          "1887-06-28",
          "1887-06-29",
          "1887-06-30"
        ],
        "wikipedia": "https:\/\/de.wikipedia.org\/wiki\/Wien",
        "geonames": "https:\/\/sws.geonames.org\/2761369\/",
        "title": "Wien",
        "type": "Verwaltungsgebiet Administrative district",
        "wikidata": "http:\/\/www.wikidata.org\/entity\/Q1741",
        "id": "pmb50"
      },
      "type": "Feature"
    },
    {
      "geometry": {
        "type": "Point",
        "coordinates": [ 16.363819, 48.20334 ]
      },
      "properties": {
        "abbr": "Ordination",
        "importance": 30,
        "timestamp": [
          "1887-06-01",
          "1887-06-02",
          "1887-06-03",
          "1887-06-04",
          "1887-06-05",
          "1887-06-06",
          "1887-06-07",
          "1887-06-08",
          "1887-06-09",
          "1887-06-10",
          "1887-06-11",
          "1887-06-12",
          "1887-06-13",
          "1887-06-14",
          "1887-06-15",
          "1887-06-16",
          "1887-06-17",
          "1887-06-18",
          "1887-06-19",
          "1887-06-20",
          "1887-06-21",
          "1887-06-22",
          "1887-06-23",
          "1887-06-24",
          "1887-06-25",
          "1887-06-26",
          "1887-06-27",
          "1887-06-28",
          "1887-06-29",
          "1887-06-30"
        ],
        "title": "Wohnung und Ordination Johann Schnitzler Burgring 1",
        "type": "Ordination Medical practice",
        "id": "pmb168765"
      },
      "type": "Feature"
    },
    {
      "geometry": {
        "type": "Point",
        "coordinates": [ 16.36645, 48.20778 ]
      },
      "properties": {
        "abbr": "Theater (K.THE)",
        "importance": 6,
        "timestamp": [ "1887-06-08", "1887-06-12", "1887-06-16", "1887-06-20", "1887-06-24", "1887-06-28" ],
        "title": "Burgtheater [Altes Burgtheater]",
        "type": "Theater Theatre",
        "wikidata": "http:\/\/www.wikidata.org\/entity\/Q45350189",
        "id": "pmb185621"
      },
      "type": "Feature"
    }
  ]
}