{
  "type": "FeatureCollection",
  "features": [
    {
      "type": "Feature",
      "geometry": {
        "type": "Point",
        "coordinates": [
          15.84704, 47.70466
        ]
      },
      "properties": {
        "name": "02. Januar 1869"
      }
    }
  ]
}